LICENSE
MANIFEST.in
README.md
setup.py
YtelAPI/__init__.py
YtelAPI/api_helper.py
YtelAPI/configuration.py
YtelAPI/decorators.py
YtelAPI/ytel_api_client.py
YtelAPI.egg-info/PKG-INFO
YtelAPI.egg-info/SOURCES.txt
YtelAPI.egg-info/dependency_links.txt
YtelAPI.egg-info/requires.txt
YtelAPI.egg-info/top_level.txt
YtelAPI/controllers/__init__.py
YtelAPI/controllers/account_controller.py
YtelAPI/controllers/base_controller.py
YtelAPI/controllers/carrier_controller.py
YtelAPI/controllers/conference_controller.py
YtelAPI/controllers/dedicated_short_code_controller.py
YtelAPI/controllers/email_controller.py
YtelAPI/controllers/phone_number_controller.py
YtelAPI/controllers/recording_controller.py
YtelAPI/controllers/shared_short_code_controller.py
YtelAPI/controllers/sms_controller.py
YtelAPI/controllers/sub_account_controller.py
YtelAPI/controllers/transcription_controller.py
YtelAPI/controllers/usage_controller.py
YtelAPI/controllers/voice_controller.py
YtelAPI/exceptions/__init__.py
YtelAPI/exceptions/api_exception.py
YtelAPI/http/__init__.py
YtelAPI/http/http_call_back.py
YtelAPI/http/http_client.py
YtelAPI/http/http_context.py
YtelAPI/http/http_method_enum.py
YtelAPI/http/http_request.py
YtelAPI/http/http_response.py
YtelAPI/http/requests_client.py
YtelAPI/http/auth/__init__.py
YtelAPI/http/auth/basic_auth.py
YtelAPI/models/__init__.py
YtelAPI/models/activate_enum.py
YtelAPI/models/audio_direction_enum.py
YtelAPI/models/audio_url_enum.py
YtelAPI/models/body.py
YtelAPI/models/body_1.py
YtelAPI/models/body_10.py
YtelAPI/models/body_11.py
YtelAPI/models/body_12.py
YtelAPI/models/body_13.py
YtelAPI/models/body_14.py
YtelAPI/models/body_16.py
YtelAPI/models/body_17.py
YtelAPI/models/body_18.py
YtelAPI/models/body_19.py
YtelAPI/models/body_2.py
YtelAPI/models/body_20.py
YtelAPI/models/body_21.py
YtelAPI/models/body_22.py
YtelAPI/models/body_23.py
YtelAPI/models/body_24.py
YtelAPI/models/body_25.py
YtelAPI/models/body_26.py
YtelAPI/models/body_27.py
YtelAPI/models/body_28.py
YtelAPI/models/body_29.py
YtelAPI/models/body_3.py
YtelAPI/models/body_30.py
YtelAPI/models/body_31.py
YtelAPI/models/body_32.py
YtelAPI/models/body_33.py
