Metadata-Version: 1.0
Name: YtelAPI
Version: 3.1.3
Summary: Ytel API version 3.1.2
Home-page: https://apimatic.io
Author: APIMatic SDK Generator
Author-email: support@apimatic.io
License: UNKNOWN
Platform: UNKNOWN
